{
    "version": "3.25.6",
    "description": "AdNauseam: Fight back against advertising surveillance",
    "homepage": "https://github.com/dhowe/AdNauseam",
    "license": "GPL-3.0",
    "url": "https://gh-proxy.com/https://github.com/dhowe/AdNauseam/releases/download/v3.25.6/adnauseam-3.25.6.chromium.zip",
    "hash": "c4ee747073b0b3017deb8b54b8c3e942994689fa7fad1da67250ec603c6b84e9",
    "checkver": "github",
    "autoupdate": {
        "url": "https://gh-proxy.com/https://github.com/dhowe/AdNauseam/releases/download/v$version/adnauseam-$version.chromium.zip"
    },
    "notes": "Install this extension manually via Chrome's extensions page in developer mode."
}
